{
  "$schema": "http://json-schema.org/draft-04/schema#",
  "title": "Dataset",
  "description": "Describes a dataset, and gives associated bibliographic informations. Datasets are a collection of networks, published in one or several studies.",
  "type": "object",
  "properties": {
    "id": {
      "description": "Access code for the dataset in the local database.",
      "type": "string"
    },
    "name": {
    	"description": "Name of the dataset",
      "type": "string"
    },
    "description": {
       "description": "A short description of the dataset.",
       "type": "string"
    },
    "papers": {
       "description": "ID of the reference resource for the paper(s) in which the dataset was first published/used, or other significant papers related to this dataset.",
       "type": "array",
       "items": {
          "type": "string",
       }
    },
    "data": {
       "description": "ID of the resource for the data themselves (i.e. data paper, figshare or datadryad DOI, ...)",
       "type": "array",
       "items": {
          "type": "string"
       }
    },
    "networks": {
       "description": "List of networks ID",
       "type": "array",
       "items": {
          "type": "string"
       },
       "uniqueItems": true
    }
  },
  "required": ["name", "networks"]
}
